README.txt
setup.cfg
setup.py
nsi/__init__.py
nsi.svgtool.egg-info/PKG-INFO
nsi.svgtool.egg-info/SOURCES.txt
nsi.svgtool.egg-info/dependency_links.txt
nsi.svgtool.egg-info/entry_points.txt
nsi.svgtool.egg-info/namespace_packages.txt
nsi.svgtool.egg-info/not-zip-safe
nsi.svgtool.egg-info/requires.txt
nsi.svgtool.egg-info/top_level.txt
nsi/svgtool/SvgFile-old.py
nsi/svgtool/SvgFile.py
nsi/svgtool/SvgImage.py
nsi/svgtool/SvgTool.py
nsi/svgtool/SvgXmlTool.py
nsi/svgtool/__init__.py