Metadata-Version: 1.0
Name: nsi.svgtool
Version: 0.3
Summary: UNKNOWN
Home-page: http://nsi.iff.edu.br
Author: Leandro Cruz
Author-email: lmvcruz@gmail.com
License: GPL
Platform: UNKNOWN
Classifier: Programming Language :: Python
Classifier: Topic :: Software Development :: Libraries :: Python Modules
